mdtest/__init__.py
mdtest/__main__.py
mdtest/codegenerator.py
mdtest/commandgenerators.py
mdtest/discover.py
mdtest/linefixer.py
mdtest/main.py
mdtest/markdownparser.py
mdtest/mdcompiler.py
mdtest/problemreporter.py
mdtest/structures.py
mdtest/testrunner.py
mdtest/fixture/fixture_basic.py
mdtest/fixture/fixture_cli.py
mdtest/fixture/fixture_example_concordion.py
mdtest-0.0.1.data/scripts/mdtest
mdtest-0.0.1.dist-info/LICENSE
mdtest-0.0.1.dist-info/METADATA
mdtest-0.0.1.dist-info/WHEEL
mdtest-0.0.1.dist-info/top_level.txt
mdtest-0.0.1.dist-info/zip-safe
mdtest-0.0.1.dist-info/RECORD
